langfuse_mcp/__init__.py
langfuse_mcp/__main__.py
langfuse_mcp-0.3.4.dist-info/METADATA
langfuse_mcp-0.3.4.dist-info/WHEEL
langfuse_mcp-0.3.4.dist-info/entry_points.txt
langfuse_mcp-0.3.4.dist-info/licenses/LICENSE
langfuse_mcp-0.3.4.dist-info/RECORD
