Metadata-Version: 2.4
Name: langfuse-mcp
Version: 0.3.4
Summary: Langfuse MCP server for accessing and analyzing telemetry data via natural language
Project-URL: Homepage, https://github.com/avivsinai/langfuse-mcp
Project-URL: Repository, https://github.com/avivsinai/langfuse-mcp
Project-URL: Issues, https://github.com/avivsinai/langfuse-mcp/issues
Author-email: Aviv Sinai <avivsinai@gmail.com>
License: MIT
License-File: LICENSE
Classifier: Development Status :: 4 - Beta
Classifier: Intended Audience :: Developers
Classifier: License :: OSI Approved :: MIT License
Classifier: Programming Language :: Python :: 3
Classifier: Programming Language :: Python :: 3 :: Only
Classifier: Programming Language :: Python :: 3.10
Classifier: Programming Language :: Python :: 3.11
Classifier: Programming Language :: Python :: 3.12
Classifier: Programming Language :: Python :: 3.13
Requires-Python: <3.14,>=3.10
Requires-Dist: cachetools>=5.0.0
Requires-Dist: langfuse<4.0.0,>=3.11.2
Requires-Dist: mcp[cli]>=1.6.0
Requires-Dist: pydantic>=2.0.0
Provides-Extra: dev
Requires-Dist: pytest; extra == 'dev'
Requires-Dist: pytest-asyncio; extra == 'dev'
Requires-Dist: pytest-mock; extra == 'dev'
Requires-Dist: ruff; extra == 'dev'
